pulpy/__init__.py
pulpy/grad/__init__.py
pulpy/grad/optim.py
pulpy/grad/waveform.py
pulpy/io.py
pulpy/linop.py
pulpy/rf/__init__.py
pulpy/rf/adiabatic.py
pulpy/rf/b1sel.py
pulpy/rf/multiband.py
pulpy/rf/optcont.py
pulpy/rf/ptx.py
pulpy/rf/shim.py
pulpy/rf/slr.py
pulpy/rf/util.py
pulpy/sim.py
pulpy/verse.py
pulpy/version.py
pulpy-1.8.8.dist-info/LICENSE
pulpy-1.8.8.dist-info/METADATA
pulpy-1.8.8.dist-info/WHEEL
pulpy-1.8.8.dist-info/RECORD
