Metadata-Version: 2.1
Name: pulpy
Version: 1.8.8
Summary: PulPy: Pulses in Python. A package for MRI RF and gradient pulse design.
Home-page: https://github.com/jonbmartin/pulpy
License: MIT
Author: jonbmartin
Author-email: jon.bach.martin@gmail.com
Requires-Python: >=3.10,<4.0
Classifier: License :: OSI Approved :: MIT License
Classifier: Programming Language :: Python :: 3
Classifier: Programming Language :: Python :: 3.10
Classifier: Programming Language :: Python :: 3.11
Classifier: Programming Language :: Python :: 3.12
Classifier: Programming Language :: Python :: 3.13
Classifier: Topic :: Scientific/Engineering
Requires-Dist: numba (>=0.59.1,<0.60.0)
Requires-Dist: numpy (>=1.24.4,<2.0.0)
Requires-Dist: scipy (>=1.13.1,<2.0.0)
Requires-Dist: sigpy (>=0.1.26,<0.2.0)
Project-URL: Repository, https://github.com/jonbmartin/pulpy
